dist_operations
